algoql/__init__.py
algoql/algoql.py
algoql/algoql.tx
algoql/algorand.py
algoql/cli.py
algoql-0.0.2.dist-info/LICENSE.txt
algoql-0.0.2.dist-info/METADATA
algoql-0.0.2.dist-info/WHEEL
algoql-0.0.2.dist-info/entry_points.txt
algoql-0.0.2.dist-info/top_level.txt
algoql-0.0.2.dist-info/RECORD
