Metadata-Version: 2.1
Name: algoql
Version: 0.0.2
Summary: Algorand streaming Query Language
Author-email: Marcin Zawiejski <dragmz@gmail.com>
Requires-Python: >=3.9
License-File: LICENSE.txt
Requires-Dist: textX (>=3.0.0)
Requires-Dist: py-algorand-sdk (>=1.20.1)
